random_letter/__init__.py
random_letter/random_letter.py
random_letter-0.0.3.dist-info/METADATA
random_letter-0.0.3.dist-info/WHEEL
random_letter-0.0.3.dist-info/licenses/LICENSE
random_letter-0.0.3.dist-info/RECORD
